{
  "id": 8335115550808,
  "title": "Seashell Abstract Cake Google Pixel 9 Pro XL Case",
  "handle": "seashell-abstract-cake-eco-friendly-google-pixel-9-pro-xl-case",
  "body_html": "<p><meta charset=\"utf-8\">Meet the Abstract Cake Phone Case—a slice of bold, funky fun for your phone. With layers of vibrant patterns, playful florals, and just the right amount of visual chaos, this case serves sweet style with a side of attitude. It’s like your favorite dessert and a pop art gallery had a design baby—and yes, it’s drop-proof too. 🍰📱💥</p>\n<p>Beautifully designed, Pela cases are the world's first truly sustainable phone case. They are durable enough to protect your phone from drops and scratches and are also compostable!</p>",
  "published_at": "2025-04-22T09:16:43-04:00",
  "created_at": "2025-04-01T11:42:06-04:00",
  "updated_at": "2025-09-22T15:14:29-04:00",
  "vendor": "Pela Case",
  "product_type": "Google Pixel 9 Pro XL",
  "tags": [
    "art-type:Print",
    "collection:Mix and Maximalist",
    "Made to Order",
    "made-in:north-america",
    "name:Abstract Cake",
    "Phone Case",
    "product_notice_2",
    "protection-level:2"
  ],
  "variants": [
    {
      "id": 42788474585176,
      "title": "Default Title",
      "option1": "Default Title",
      "option2": null,
      "option3": null,
      "sku": "blank:15696-PX9PXL-SEASHELL-AOD:ABSTRACT-CAKE",
      "requires_shipping": true,
      "taxable": true,
      "featured_image": null,
      "available": true,
      "price": "65.00",
      "grams": 0,
      "compare_at_price": "65.00",
      "position": 1,
      "product_id": 8335115550808,
      "created_at": "2025-04-01T11:42:06-04:00",
      "updated_at": "2025-09-22T15:14:29-04:00"
    }
  ],
  "images": [
    {
      "id": 34775473422424,
      "created_at": "2025-04-01T11:42:06-04:00",
      "position": 1,
      "updated_at": "2025-04-01T11:42:08-04:00",
      "product_id": 8335115550808,
      "variant_ids": [],
      "src": "https://cdn.shopify.com/s/files/1/0078/1032/files/ABSTRACT-CAKE_PX9PXL_Seashell.jpg?v=1743522128",
      "width": 2000,
      "height": 2000
    },
    {
      "id": 34892727255128,
      "created_at": "2025-04-23T10:32:12-04:00",
      "position": 2,
      "updated_at": "2025-04-23T10:32:17-04:00",
      "product_id": 8335115550808,
      "variant_ids": [],
      "src": "https://cdn.shopify.com/s/files/1/0078/1032/files/MixMax_Render_Group_Friends_PDP_1x1_01_318b5752-87f3-4f61-8a9b-cede56147ce2.jpg?v=1745418737",
      "width": 810,
      "height": 810
    },
    {
      "id": 34892727222360,
      "created_at": "2025-04-23T10:32:12-04:00",
      "position": 3,
      "updated_at": "2025-04-23T10:32:17-04:00",
      "product_id": 8335115550808,
      "variant_ids": [],
      "src": "https://cdn.shopify.com/s/files/1/0078/1032/files/MixMax_Render_Group_Androids_PDP_1x1_03_19181563-5851-4919-a43f-eb383e791b59.jpg?v=1745418737",
      "width": 810,
      "height": 810
    },
    {
      "id": 34892727189592,
      "created_at": "2025-04-23T10:32:12-04:00",
      "position": 4,
      "updated_at": "2025-04-23T10:32:17-04:00",
      "product_id": 8335115550808,
      "variant_ids": [],
      "src": "https://cdn.shopify.com/s/files/1/0078/1032/files/MixMax_Render_Group_IPGrid_PDP_1x1_05_1b9203fd-80b6-4434-91b5-d3e59bc9f5f9.jpg?v=1745418737",
      "width": 810,
      "height": 810
    }
  ],
  "options": [
    {
      "name": "Title",
      "position": 1,
      "values": [
        "Default Title"
      ]
    }
  ],
  "price": 65,
  "compare_at_price": 65,
  "featured_image_url": "https://cdn.shopify.com/s/files/1/0078/1032/files/ABSTRACT-CAKE_PX9PXL_Seashell.jpg?v=1743522128",
  "images_count": 4,
  "variants_count": 1,
  "status": "active",
  "brand": "Pela Case",
  "category": "Google Pixel 9 Pro XL",
  "availability": "in stock",
  "condition": "new",
  "dimensions": {}
}