{
  "id": 6805423587530,
  "title": "Gymshark Everyday Seamless Long Sleeve Top - Black",
  "handle": "gymshark-everyday-seamless-long-sleeve-top-black-ss24",
  "body_html": "<p><strong>ADD A LITTLE EXTRA</strong></p>\n<p><br data-mce-fragment=\"1\">These collections take your staples and give you something a little bit extra.</p>\n<p><br></p>\n<p>• Lightweight seamless material, great for running, cycling, light exercise, or just relaxing on your days off.</p>\n<p><br data-mce-fragment=\"1\"><strong>Note:</strong><br data-mce-fragment=\"1\">The Everyday collection isn't designed for heavy lifting or high-intensity training. To make it comfy af, the collection's made with a lightweight seamless material that can become sheer when it’s stretched.</p>\n<p><br data-mce-fragment=\"1\"><strong>SIZE &amp; FIT</strong><br data-mce-fragment=\"1\">• Regular fit<br data-mce-fragment=\"1\">• Model 1 is 5'8\" and wears size XS<br>• Model 2 is 5'10\" and wears size L<br></p>\n<p><br data-mce-fragment=\"1\"><strong>MATERIALS &amp; CARE</strong><br data-mce-fragment=\"1\">• 100% Nylon</p>\n<p><br data-mce-fragment=\"1\">SKU: B8A4Q-BB2J</p>",
  "published_at": "2024-01-12T09:32:01-08:00",
  "created_at": "2023-07-25T10:01:02-07:00",
  "updated_at": "2025-09-22T08:45:58-07:00",
  "vendor": "Gymshark | Be a visionary.",
  "product_type": "Womens Ls Tops",
  "tags": [
    "activity:Conditioning",
    "akeneo_updated_at:1758011277",
    "all-products",
    "black-gym-sets",
    "black-staples",
    "black-tops",
    "build-your-wishlist",
    "category:LS Tops",
    "conditioning",
    "created_by:product-service",
    "division:Apparel",
    "everyday",
    "everyday-black",
    "everyday-seamless",
    "feature: seamless",
    "feature:lightweight",
    "filter-colour:Black",
    "fit:Regular Fit",
    "garmentLength:Regular Fit",
    "long-sleeve",
    "lower-bucket",
    "matching-sets",
    "must-have",
    "over-40-off",
    "over-50-off",
    "over-60-off",
    "over-70-off",
    "percentageInStockV2",
    "range:Essentials",
    "sale-t-shirts-tops",
    "seamless",
    "seamless-sets",
    "seamless-tops",
    "seamtype:Seamless",
    "season:SS24",
    "seasonal-essentials",
    "segmentation:Conditioning",
    "sizeguide:top",
    "subcategory:Crew Neck",
    "t-shirts-tops",
    "tier:1",
    "Womens"
  ],
  "variants": [
    {
      "id": 39791303000266,
      "title": "Extra Extra Small",
      "option1": "Extra Extra Small",
      "option2": null,
      "option3": null,
      "sku": "B8A4Q-BB2J-XXS",
      "requires_shipping": true,
      "taxable": true,
      "featured_image": null,
      "available": false,
      "price": "28.00",
      "grams": 0,
      "compare_at_price": null,
      "position": 1,
      "product_id": 6805423587530,
      "created_at": "2024-01-08T03:12:33-08:00",
      "updated_at": "2025-09-22T08:45:58-07:00"
    },
    {
      "id": 39789848264906,
      "title": "Extra Small",
      "option1": "Extra Small",
      "option2": null,
      "option3": null,
      "sku": "B8A4Q-BB2J-XS",
      "requires_shipping": true,
      "taxable": true,
      "featured_image": null,
      "available": true,
      "price": "28.00",
      "grams": 0,
      "compare_at_price": null,
      "position": 2,
      "product_id": 6805423587530,
      "created_at": "2023-07-25T10:02:14-07:00",
      "updated_at": "2025-09-22T08:45:58-07:00"
    },
    {
      "id": 39789844693194,
      "title": "Small",
      "option1": "Small",
      "option2": null,
      "option3": null,
      "sku": "B8A4Q-BB2J-S",
      "requires_shipping": true,
      "taxable": true,
      "featured_image": null,
      "available": true,
      "price": "28.00",
      "grams": 0,
      "compare_at_price": null,
      "position": 3,
      "product_id": 6805423587530,
      "created_at": "2023-07-25T10:01:38-07:00",
      "updated_at": "2025-09-22T08:45:58-07:00"
    },
    {
      "id": 39789840957642,
      "title": "Medium",
      "option1": "Medium",
      "option2": null,
      "option3": null,
      "sku": "B8A4Q-BB2J-M",
      "requires_shipping": true,
      "taxable": true,
      "featured_image": null,
      "available": true,
      "price": "28.00",
      "grams": 0,
      "compare_at_price": null,
      "position": 4,
      "product_id": 6805423587530,
      "created_at": "2023-07-25T10:01:02-07:00",
      "updated_at": "2025-09-22T08:45:58-07:00"
    },
    {
      "id": 39789844594890,
      "title": "Large",
      "option1": "Large",
      "option2": null,
      "option3": null,
      "sku": "B8A4Q-BB2J-L",
      "requires_shipping": true,
      "taxable": true,
      "featured_image": null,
      "available": true,
      "price": "28.00",
      "grams": 0,
      "compare_at_price": null,
      "position": 5,
      "product_id": 6805423587530,
      "created_at": "2023-07-25T10:01:37-07:00",
      "updated_at": "2025-09-22T08:45:58-07:00"
    },
    {
      "id": 39789854654666,
      "title": "Extra Large",
      "option1": "Extra Large",
      "option2": null,
      "option3": null,
      "sku": "B8A4Q-BB2J-XL",
      "requires_shipping": true,
      "taxable": true,
      "featured_image": null,
      "available": true,
      "price": "28.00",
      "grams": 0,
      "compare_at_price": null,
      "position": 6,
      "product_id": 6805423587530,
      "created_at": "2023-07-25T10:08:12-07:00",
      "updated_at": "2025-09-22T08:45:58-07:00"
    },
    {
      "id": 39789842923722,
      "title": "Extra Extra Large",
      "option1": "Extra Extra Large",
      "option2": null,
      "option3": null,
      "sku": "B8A4Q-BB2J-XXL",
      "requires_shipping": true,
      "taxable": true,
      "featured_image": null,
      "available": true,
      "price": "28.00",
      "grams": 0,
      "compare_at_price": null,
      "position": 7,
      "product_id": 6805423587530,
      "created_at": "2023-07-25T10:01:24-07:00",
      "updated_at": "2025-09-22T08:45:58-07:00"
    }
  ],
  "images": [
    {
      "id": 28978568593610,
      "created_at": "2024-03-18T08:17:43-07:00",
      "position": 1,
      "updated_at": "2024-03-18T08:17:51-07:00",
      "product_id": 6805423587530,
      "variant_ids": [],
      "src": "https://cdn.shopify.com/s/files/1/0156/6146/files/EverydaySeamlessLongSleeveTopGSBlackB8A4Q-BB2J0685_5c63716b-bdcc-4dd6-99d2-16b8bec99ffc.jpg?v=1710775071",
      "width": 1692,
      "height": 2018
    },
    {
      "id": 28978570100938,
      "created_at": "2024-03-18T08:17:43-07:00",
      "position": 2,
      "updated_at": "2024-03-18T08:17:52-07:00",
      "product_id": 6805423587530,
      "variant_ids": [],
      "src": "https://cdn.shopify.com/s/files/1/0156/6146/files/EverydaySeamlessLongSleeveTopGSBlackB8A4Q-BB2J0687.jpg?v=1710775072",
      "width": 1692,
      "height": 2018
    },
    {
      "id": 28978571051210,
      "created_at": "2024-03-18T08:17:43-07:00",
      "position": 3,
      "updated_at": "2024-03-18T08:17:53-07:00",
      "product_id": 6805423587530,
      "variant_ids": [],
      "src": "https://cdn.shopify.com/s/files/1/0156/6146/files/EverydaySeamlessLongSleeveTopGSBlackB8A4Q-BB2J10431_ZH.jpg?v=1710775073",
      "width": 2538,
      "height": 3027
    },
    {
      "id": 28978565447882,
      "created_at": "2024-03-18T08:17:43-07:00",
      "position": 4,
      "updated_at": "2024-03-18T08:17:49-07:00",
      "product_id": 6805423587530,
      "variant_ids": [],
      "src": "https://cdn.shopify.com/s/files/1/0156/6146/files/EverydaySeamlessLongSleeveTopGSBlackB8A4Q-BB2J0689.jpg?v=1710775069",
      "width": 1692,
      "height": 2018
    },
    {
      "id": 28978562564298,
      "created_at": "2024-03-18T08:17:43-07:00",
      "position": 5,
      "updated_at": "2024-03-18T08:17:47-07:00",
      "product_id": 6805423587530,
      "variant_ids": [],
      "src": "https://cdn.shopify.com/s/files/1/0156/6146/files/EverydaySeamlessLongSleeveTopGSBlackB8A4Q-BB2J10551_ZH.jpg?v=1710775067",
      "width": 2538,
      "height": 3027
    },
    {
      "id": 28978560958666,
      "created_at": "2024-03-18T08:17:43-07:00",
      "position": 6,
      "updated_at": "2024-03-18T08:17:46-07:00",
      "product_id": 6805423587530,
      "variant_ids": [],
      "src": "https://cdn.shopify.com/s/files/1/0156/6146/files/EverydaySeamlessLongSleeveTopGSBlackB8A4Q-BB2J0686_392a075f-5653-4587-acbe-8c24ab6d7b49.jpg?v=1710775066",
      "width": 1692,
      "height": 2018
    },
    {
      "id": 28978567086282,
      "created_at": "2024-03-18T08:17:43-07:00",
      "position": 7,
      "updated_at": "2024-03-18T08:17:50-07:00",
      "product_id": 6805423587530,
      "variant_ids": [],
      "src": "https://cdn.shopify.com/s/files/1/0156/6146/files/EverydaySeamlessLongSleeveTopGSBlackB8A4Q-BB2J0688_d2be9a23-34f1-4856-ad3f-f7f1c3a3ed1b.jpg?v=1710775070",
      "width": 1692,
      "height": 2018
    }
  ],
  "options": [
    {
      "name": "Size",
      "position": 1,
      "values": [
        "Extra Extra Small",
        "Extra Small",
        "Small",
        "Medium",
        "Large",
        "Extra Large",
        "Extra Extra Large"
      ]
    }
  ],
  "price": 28,
  "featured_image_url": "https://cdn.shopify.com/s/files/1/0156/6146/files/EverydaySeamlessLongSleeveTopGSBlackB8A4Q-BB2J0685_5c63716b-bdcc-4dd6-99d2-16b8bec99ffc.jpg?v=1710775071",
  "images_count": 7,
  "variants_count": 7,
  "status": "active",
  "brand": "Gymshark | Be a visionary.",
  "category": "Womens Ls Tops",
  "availability": "in stock",
  "condition": "new",
  "dimensions": {}
}