{
  "id": 4847863234638,
  "title": "Gymshark Flex Sports Long Sleeve Crop Top - Navy Marl/Light Grey",
  "handle": "gymshark-flex-sports-long-sleeve-crop-top-navy-marl-light-grey",
  "body_html": "<meta charset=\"utf-8\"><meta charset=\"utf-8\"><strong data-mce-fragment=\"1\">FLEXPRESS YOURSELF<span data-mce-fragment=\"1\"> </span></strong><br data-mce-fragment=\"1\"><br data-mce-fragment=\"1\"><span data-mce-fragment=\"1\">- Round Neckline</span><br data-mce-fragment=\"1\"><span data-mce-fragment=\"1\">- Long sleeves</span><br data-mce-fragment=\"1\"><span data-mce-fragment=\"1\">- Thumb holes to cuffs</span><br data-mce-fragment=\"1\"><span data-mce-fragment=\"1\">- Cut out to back</span><br data-mce-fragment=\"1\"><span data-mce-fragment=\"1\">- Seamless shading to body</span><br data-mce-fragment=\"1\"><span data-mce-fragment=\"1\"><meta charset=\"utf-8\">- Sweat-wicking fabric<br data-mce-fragment=\"1\">- Heat sealed branding to front</span><br data-mce-fragment=\"1\"><span data-mce-fragment=\"1\">- Jacquard branding to back</span><br data-mce-fragment=\"1\"><span data-mce-fragment=\"1\">- 57% Polyamide, 36% Polyester, 7% Elastane</span><br data-mce-fragment=\"1\"><span data-mce-fragment=\"1\">- Model is 5'6\" and wears size S</span><br data-mce-fragment=\"1\"><span data-mce-fragment=\"1\">- Video model is 5'7\" and wears size S</span><br data-mce-fragment=\"1\"><span data-mce-fragment=\"1\">- Label colour: Navy Marl/Light Grey</span><br data-mce-fragment=\"1\"><br data-mce-fragment=\"1\"><span data-mce-fragment=\"1\">Flex your way in the Flex Sports Long Sleeve Crop Top. Made with seamless, sweat-wicking fabric that will move with you through even your toughest workout. The flattering silhouette, cut out and bold logo give you a base piece perfect to create your own look. </span><br>",
  "published_at": "2023-11-15T17:00:21-08:00",
  "created_at": "2020-10-06T06:52:42-07:00",
  "updated_at": "2025-09-22T08:46:01-07:00",
  "vendor": "Gymshark | Be a visionary.",
  "product_type": "Womens Crop Top",
  "tags": [
    "%IS-refresh",
    "12/10/20",
    "20EXTRA",
    "activity: lifting",
    "algolia",
    "aw20",
    "bf-23",
    "crop-tops",
    "discontinued-live22",
    "ecom-video",
    "evergreen",
    "filter-colour: Blue",
    "filter-size:l",
    "filter-size:m",
    "filter-size:s",
    "filter-size:xl",
    "filter-size:xs",
    "final-sale",
    "Flex",
    "instock:xl",
    "lifting",
    "long-sleeve",
    "long-sleeve-crop-tops",
    "lq-11.7.23",
    "lq-full",
    "no-return: 2023-11-07T08:00:00_2025-11-27T00:00:0",
    "no-returns",
    "no-returns: 2023-11-27T08:00:00_2023-11-29T00:00:01",
    "no-returns: 2023-11-30T1:00:00_2025-07-10T13:00:01",
    "no-returns:2022-12-01T09:00:00_2023-12-01T12:00:00",
    "no-returns:2023-05-18T09:00:00_2023-05-30T09:00:00",
    "no-returns:2023-07-10T15:00:00_2032-05-30T09:00:00",
    "no-returns:2023-11-16T00:01:00_2023-12-01T12:00",
    "no-returns:2024-03-19T12:10:00_2024-03-19T08:00:00",
    "no-returns:2024-04-25T08:10:00_2024-04-25T08:00:00",
    "no-returns:2024-07-08T08:00:00_2032-07-02T08:00:00",
    "retention-collection",
    "sizeguide:top",
    "t-shirts-tops",
    "us-lq-3-24",
    "use code CYBER20",
    "webhooks-active",
    "willRestock",
    "Womens"
  ],
  "variants": [
    {
      "id": 32660152877134,
      "title": "Extra Small",
      "option1": "Extra Small",
      "option2": null,
      "option3": null,
      "sku": "GLCT4249-NVM/GL-XS",
      "requires_shipping": true,
      "taxable": true,
      "featured_image": null,
      "available": false,
      "price": "40.00",
      "grams": 0,
      "compare_at_price": null,
      "position": 1,
      "product_id": 4847863234638,
      "created_at": "2020-10-06T06:52:43-07:00",
      "updated_at": "2025-09-22T08:46:01-07:00"
    },
    {
      "id": 32660152909902,
      "title": "Small",
      "option1": "Small",
      "option2": null,
      "option3": null,
      "sku": "GLCT4249-NVM/GL-S",
      "requires_shipping": true,
      "taxable": true,
      "featured_image": null,
      "available": false,
      "price": "40.00",
      "grams": 0,
      "compare_at_price": null,
      "position": 2,
      "product_id": 4847863234638,
      "created_at": "2020-10-06T06:52:43-07:00",
      "updated_at": "2025-09-22T08:46:01-07:00"
    },
    {
      "id": 32660152942670,
      "title": "Medium",
      "option1": "Medium",
      "option2": null,
      "option3": null,
      "sku": "GLCT4249-NVM/GL-M",
      "requires_shipping": true,
      "taxable": true,
      "featured_image": null,
      "available": false,
      "price": "40.00",
      "grams": 0,
      "compare_at_price": null,
      "position": 3,
      "product_id": 4847863234638,
      "created_at": "2020-10-06T06:52:43-07:00",
      "updated_at": "2025-09-22T08:46:01-07:00"
    },
    {
      "id": 32660153008206,
      "title": "Large",
      "option1": "Large",
      "option2": null,
      "option3": null,
      "sku": "GLCT4249-NVM/GL-L",
      "requires_shipping": true,
      "taxable": true,
      "featured_image": null,
      "available": false,
      "price": "40.00",
      "grams": 0,
      "compare_at_price": null,
      "position": 4,
      "product_id": 4847863234638,
      "created_at": "2020-10-06T06:52:43-07:00",
      "updated_at": "2025-09-22T08:46:01-07:00"
    },
    {
      "id": 32660153040974,
      "title": "Extra Large",
      "option1": "Extra Large",
      "option2": null,
      "option3": null,
      "sku": "GLCT4249-NVM/GL-XL",
      "requires_shipping": true,
      "taxable": true,
      "featured_image": null,
      "available": false,
      "price": "40.00",
      "grams": 0,
      "compare_at_price": null,
      "position": 5,
      "product_id": 4847863234638,
      "created_at": "2020-10-06T06:52:43-07:00",
      "updated_at": "2025-09-22T08:46:01-07:00"
    }
  ],
  "images": [
    {
      "id": 28971599921354,
      "created_at": "2022-03-25T09:13:37-07:00",
      "position": 1,
      "updated_at": "2022-03-25T09:13:39-07:00",
      "product_id": 4847863234638,
      "variant_ids": [],
      "src": "https://cdn.shopify.com/s/files/1/0156/6146/products/FLEXCROPTOPNAVYMARLLIGHTGREY.A-Edit_BK_0840e96a-3ccb-4835-a119-f69d5b54d0bb.jpg?v=1648224819",
      "width": 1692,
      "height": 2018
    },
    {
      "id": 28971600183498,
      "created_at": "2022-03-25T09:13:38-07:00",
      "position": 2,
      "updated_at": "2022-03-25T09:13:40-07:00",
      "product_id": 4847863234638,
      "variant_ids": [],
      "src": "https://cdn.shopify.com/s/files/1/0156/6146/products/FLEXCROPTOPNAVYMARLLIGHTGREY.B-Edit_BK_90151516-a8e2-4b78-82c9-32a21171e951.jpg?v=1648224820",
      "width": 1692,
      "height": 2018
    },
    {
      "id": 28971600216266,
      "created_at": "2022-03-25T09:13:38-07:00",
      "position": 3,
      "updated_at": "2022-03-25T09:13:40-07:00",
      "product_id": 4847863234638,
      "variant_ids": [],
      "src": "https://cdn.shopify.com/s/files/1/0156/6146/products/FLEXCROPTOPNAVYMARLLIGHTGREY.C-Edit_BK_331c78c5-474e-4d1f-9ab4-65bbd82a58cb.jpg?v=1648224820",
      "width": 1691,
      "height": 2018
    },
    {
      "id": 28971600380106,
      "created_at": "2022-03-25T09:13:38-07:00",
      "position": 4,
      "updated_at": "2022-03-25T09:13:40-07:00",
      "product_id": 4847863234638,
      "variant_ids": [],
      "src": "https://cdn.shopify.com/s/files/1/0156/6146/products/FLEXCROPTOPNAVYMARLLIGHTGREY.D1-Edit_BK_f5b31f1a-2d23-4f0c-bc46-d1d3ad072caa.jpg?v=1648224820",
      "width": 1692,
      "height": 2018
    },
    {
      "id": 28971600511178,
      "created_at": "2022-03-25T09:13:38-07:00",
      "position": 5,
      "updated_at": "2022-03-25T09:13:41-07:00",
      "product_id": 4847863234638,
      "variant_ids": [],
      "src": "https://cdn.shopify.com/s/files/1/0156/6146/products/FLEXCROPTOPNAVYMARLLIGHTGREY.D2-Edit_BK_d11fc567-15f1-4030-bce1-fe48cfa138a0.jpg?v=1648224821",
      "width": 1692,
      "height": 2018
    },
    {
      "id": 28971600117962,
      "created_at": "2022-03-25T09:13:38-07:00",
      "position": 6,
      "updated_at": "2022-03-25T09:13:39-07:00",
      "product_id": 4847863234638,
      "variant_ids": [],
      "src": "https://cdn.shopify.com/s/files/1/0156/6146/products/FLEXCROPTOPNAVYMARLLIGHTGREY.D3-Edit_BK_9be32e67-eac8-47cf-b1a7-0a514ee307f6.jpg?v=1648224819",
      "width": 1692,
      "height": 2018
    }
  ],
  "options": [
    {
      "name": "Size",
      "position": 1,
      "values": [
        "Extra Small",
        "Small",
        "Medium",
        "Large",
        "Extra Large"
      ]
    }
  ],
  "price": 40,
  "featured_image_url": "https://cdn.shopify.com/s/files/1/0156/6146/products/FLEXCROPTOPNAVYMARLLIGHTGREY.A-Edit_BK_0840e96a-3ccb-4835-a119-f69d5b54d0bb.jpg?v=1648224819",
  "images_count": 6,
  "variants_count": 5,
  "status": "active",
  "brand": "Gymshark | Be a visionary.",
  "category": "Womens Crop Top",
  "availability": "out of stock",
  "condition": "new",
  "dimensions": {}
}