{
  "id": 6805990867146,
  "title": "Gymshark Halter Neck Sports Bra - Washed Berry Pink",
  "handle": "gymshark-halter-neck-sports-bra-sports-bras-pink-ss25",
  "body_html": "<p><strong>FIND THE ONE</strong></p>\n<p><br>Whether you’re looking for HIIT-worthy high support or an everyday light alternative, our sports bras are more trustworthy, supportive and reliable than your ex.</p>\n<p><br>• Stylish high halterneck front and scooped back<br>• Make it your own with removable padding so you can choose the support based on your work out<br>• Adjustable straps for the perfect fit every time<br>• Perfect for back day</p>\n<p><br><strong>SIZE &amp; FIT</strong><br>• Light support<br>• Model is 5'8\" and wears a size S <br> <br><strong>MATERIALS &amp; CARE </strong><br>• 78% Polyester, 22% Elastane<br> <br>SKU: B3C5J-KCPS<br></p>",
  "published_at": "2025-03-05T07:38:47-08:00",
  "created_at": "2024-08-15T04:06:52-07:00",
  "updated_at": "2025-09-22T08:45:44-07:00",
  "vendor": "Gymshark | Be a visionary.",
  "product_type": "Womens Sports Bras",
  "tags": [
    "akeneo_updated_at:1754923937",
    "all-products",
    "backless-sports-bras",
    "brasupport:Light Support",
    "build-your-wishlist",
    "category:Sports Bras",
    "created_by:product-service",
    "division:Apparel",
    "filter-colour:Pink",
    "fit:light support",
    "get-the-look:B3C5J-KCPS",
    "get-the-look:B7A3L-BB2J",
    "get-the-look:I1A2B-WBBM",
    "halter-sports-bras",
    "last-chance",
    "low-support-sports-bras",
    "lower-bucket",
    "over-40-off",
    "over-50-off",
    "over-60-off",
    "over-70-off",
    "padded-sports-bras",
    "percentageInStockV2",
    "pink-gym-sets",
    "pink-sports-bras",
    "range:Fundamental Sports Bras",
    "sale-sports-bra",
    "season:SS25",
    "segmentation:Conditioning",
    "sizeguide:sportsbra",
    "sports-bras",
    "subcategory:V-Neck",
    "tier:1",
    "valentines-day",
    "Womens"
  ],
  "variants": [
    {
      "id": 39793393926346,
      "title": "Extra Extra Small",
      "option1": "Extra Extra Small",
      "option2": null,
      "option3": null,
      "sku": "B3C5J-KCPS-XXS",
      "requires_shipping": true,
      "taxable": true,
      "featured_image": null,
      "available": false,
      "price": "16.00",
      "grams": 0,
      "compare_at_price": "32.00",
      "position": 1,
      "product_id": 6805990867146,
      "created_at": "2024-08-15T04:08:38-07:00",
      "updated_at": "2025-09-22T08:45:44-07:00"
    },
    {
      "id": 39793412210890,
      "title": "Extra Small",
      "option1": "Extra Small",
      "option2": null,
      "option3": null,
      "sku": "B3C5J-KCPS-XS",
      "requires_shipping": true,
      "taxable": true,
      "featured_image": null,
      "available": true,
      "price": "16.00",
      "grams": 0,
      "compare_at_price": "32.00",
      "position": 2,
      "product_id": 6805990867146,
      "created_at": "2024-08-15T04:13:33-07:00",
      "updated_at": "2025-09-22T08:45:44-07:00"
    },
    {
      "id": 39793388683466,
      "title": "Small",
      "option1": "Small",
      "option2": null,
      "option3": null,
      "sku": "B3C5J-KCPS-S",
      "requires_shipping": true,
      "taxable": true,
      "featured_image": null,
      "available": true,
      "price": "16.00",
      "grams": 0,
      "compare_at_price": "32.00",
      "position": 3,
      "product_id": 6805990867146,
      "created_at": "2024-08-15T04:07:25-07:00",
      "updated_at": "2025-09-22T08:45:44-07:00"
    },
    {
      "id": 39793393795274,
      "title": "Medium",
      "option1": "Medium",
      "option2": null,
      "option3": null,
      "sku": "B3C5J-KCPS-M",
      "requires_shipping": true,
      "taxable": true,
      "featured_image": null,
      "available": false,
      "price": "16.00",
      "grams": 0,
      "compare_at_price": "32.00",
      "position": 4,
      "product_id": 6805990867146,
      "created_at": "2024-08-15T04:08:36-07:00",
      "updated_at": "2025-09-22T08:45:44-07:00"
    },
    {
      "id": 39793386422474,
      "title": "Large",
      "option1": "Large",
      "option2": null,
      "option3": null,
      "sku": "B3C5J-KCPS-L",
      "requires_shipping": true,
      "taxable": true,
      "featured_image": null,
      "available": false,
      "price": "16.00",
      "grams": 0,
      "compare_at_price": "32.00",
      "position": 5,
      "product_id": 6805990867146,
      "created_at": "2024-08-15T04:06:52-07:00",
      "updated_at": "2025-09-22T08:45:44-07:00"
    },
    {
      "id": 39793400774858,
      "title": "Extra Large",
      "option1": "Extra Large",
      "option2": null,
      "option3": null,
      "sku": "B3C5J-KCPS-XL",
      "requires_shipping": true,
      "taxable": true,
      "featured_image": null,
      "available": false,
      "price": "16.00",
      "grams": 0,
      "compare_at_price": "32.00",
      "position": 6,
      "product_id": 6805990867146,
      "created_at": "2024-08-15T04:10:11-07:00",
      "updated_at": "2025-09-22T08:45:44-07:00"
    },
    {
      "id": 39793395400906,
      "title": "Extra Extra Large",
      "option1": "Extra Extra Large",
      "option2": null,
      "option3": null,
      "sku": "B3C5J-KCPS-XXL",
      "requires_shipping": true,
      "taxable": true,
      "featured_image": null,
      "available": false,
      "price": "16.00",
      "grams": 0,
      "compare_at_price": "32.00",
      "position": 7,
      "product_id": 6805990867146,
      "created_at": "2024-08-15T04:08:56-07:00",
      "updated_at": "2025-09-22T08:45:44-07:00"
    }
  ],
  "images": [
    {
      "id": 28990920917194,
      "created_at": "2025-02-13T00:52:46-08:00",
      "position": 1,
      "updated_at": "2025-02-13T00:52:48-08:00",
      "product_id": 6805990867146,
      "variant_ids": [],
      "src": "https://cdn.shopify.com/s/files/1/0156/6146/files/HalterNeckSportsBraGSWashedBerryPinkB3C5J-KCPS-0272.jpg?v=1739436768",
      "width": 1692,
      "height": 2018
    },
    {
      "id": 28990921146570,
      "created_at": "2025-02-13T00:52:46-08:00",
      "position": 2,
      "updated_at": "2025-02-13T00:52:48-08:00",
      "product_id": 6805990867146,
      "variant_ids": [],
      "src": "https://cdn.shopify.com/s/files/1/0156/6146/files/HalterNeckSportsBraGSWashedBerryPinkB3C5J-KCPS-0437.jpg?v=1739436768",
      "width": 1692,
      "height": 2018
    },
    {
      "id": 28990920949962,
      "created_at": "2025-02-13T00:52:46-08:00",
      "position": 3,
      "updated_at": "2025-02-13T00:52:48-08:00",
      "product_id": 6805990867146,
      "variant_ids": [],
      "src": "https://cdn.shopify.com/s/files/1/0156/6146/files/HalterNeckSportsBraGSWashedBerryPinkB3C5J-KCPS-0432.jpg?v=1739436768",
      "width": 1692,
      "height": 2018
    },
    {
      "id": 28990920982730,
      "created_at": "2025-02-13T00:52:46-08:00",
      "position": 4,
      "updated_at": "2025-02-13T00:52:48-08:00",
      "product_id": 6805990867146,
      "variant_ids": [],
      "src": "https://cdn.shopify.com/s/files/1/0156/6146/files/HalterNeckSportsBraGSWashedBerryPinkB3C5J-KCPS-0455.jpg?v=1739436768",
      "width": 1692,
      "height": 2018
    },
    {
      "id": 28990921015498,
      "created_at": "2025-02-13T00:52:46-08:00",
      "position": 5,
      "updated_at": "2025-02-13T00:52:48-08:00",
      "product_id": 6805990867146,
      "variant_ids": [],
      "src": "https://cdn.shopify.com/s/files/1/0156/6146/files/HalterNeckSportsBraGSWashedBerryPinkB3C5J-KCPS-0423.jpg?v=1739436768",
      "width": 1692,
      "height": 2018
    }
  ],
  "options": [
    {
      "name": "Size",
      "position": 1,
      "values": [
        "Extra Extra Small",
        "Extra Small",
        "Small",
        "Medium",
        "Large",
        "Extra Large",
        "Extra Extra Large"
      ]
    }
  ],
  "price": 16,
  "compare_at_price": 32,
  "featured_image_url": "https://cdn.shopify.com/s/files/1/0156/6146/files/HalterNeckSportsBraGSWashedBerryPinkB3C5J-KCPS-0272.jpg?v=1739436768",
  "images_count": 5,
  "variants_count": 7,
  "status": "active",
  "brand": "Gymshark | Be a visionary.",
  "category": "Womens Sports Bras",
  "availability": "in stock",
  "condition": "new",
  "dimensions": {}
}