{
  "id": 6806352822474,
  "title": "Gymshark Ribbed Midi Tank With Shelf - Navy",
  "handle": "gymshark-ribbed-midi-tank-with-shelf-crop-tops-blue-aw25",
  "body_html": "<p><b>ADD A LITTLE EXTRA</b></p><p>These styles take your training staples and give you something a little bit extra.</p><ul>\n<li>Body-contouring stitching</li>\n<li>Flattering open square back</li>\n<li>Internal shelf bra for a little extra support &amp; coverage</li>\n</ul><p><br></p><p><b>SIZE &amp; FIT</b></p><ul>\n<li>Light support</li>\n<li>Body fit</li>\n<li>Midi length</li>\n<li>Model is 5'9\" and wears size S</li>\n</ul><p><br></p><p><b>MATERIALS &amp; CARE</b></p><ul><li>74% Nylon, 26% Elastane</li></ul>",
  "published_at": "2025-08-28T10:58:40-07:00",
  "created_at": "2025-02-06T03:36:31-08:00",
  "updated_at": "2025-09-22T08:44:37-07:00",
  "vendor": "Gymshark | Be a visionary.",
  "product_type": "Womens Crop Tops",
  "tags": [
    "28/08/25",
    "akeneo_updated_at:1757351973",
    "all-products",
    "blue-gym-sets",
    "build-your-wishlist",
    "built-in-bras",
    "category:Crop Tops",
    "created_by:product-service",
    "crop-tops",
    "division:Apparel",
    "filter-colour:Blue",
    "fit:Body Fit",
    "garmentLength:Midi",
    "get-the-look:B5C1H-UB9P",
    "get-the-look:B5C1R-UB9P",
    "lower-bucket",
    "new-releases",
    "over-40-off",
    "over-50-off",
    "over-60-off",
    "over-70-off",
    "percentageInStockV2",
    "range:Gym-Kit",
    "sale-t-shirts-tops",
    "segmentation:Conditioning",
    "sizeguide:top",
    "spanish-translated",
    "sports-bras",
    "subcategory:Sleeveless",
    "t-shirts-tops",
    "tier:2",
    "Womens"
  ],
  "variants": [
    {
      "id": 39795584762058,
      "title": "Extra Extra Small",
      "option1": "Extra Extra Small",
      "option2": null,
      "option3": null,
      "sku": "B5C1R-UB9P-XXS",
      "requires_shipping": true,
      "taxable": true,
      "featured_image": null,
      "available": false,
      "price": "36.00",
      "grams": 0,
      "compare_at_price": null,
      "position": 1,
      "product_id": 6806352822474,
      "created_at": "2025-02-06T04:51:09-08:00",
      "updated_at": "2025-09-22T08:44:37-07:00"
    },
    {
      "id": 39795542393034,
      "title": "Extra Small",
      "option1": "Extra Small",
      "option2": null,
      "option3": null,
      "sku": "B5C1R-UB9P-XS",
      "requires_shipping": true,
      "taxable": true,
      "featured_image": null,
      "available": true,
      "price": "36.00",
      "grams": 0,
      "compare_at_price": null,
      "position": 2,
      "product_id": 6806352822474,
      "created_at": "2025-02-06T03:38:35-08:00",
      "updated_at": "2025-09-22T08:44:37-07:00"
    },
    {
      "id": 39795569000650,
      "title": "Small",
      "option1": "Small",
      "option2": null,
      "option3": null,
      "sku": "B5C1R-UB9P-S",
      "requires_shipping": true,
      "taxable": true,
      "featured_image": null,
      "available": true,
      "price": "36.00",
      "grams": 0,
      "compare_at_price": null,
      "position": 3,
      "product_id": 6806352822474,
      "created_at": "2025-02-06T03:45:51-08:00",
      "updated_at": "2025-09-22T08:44:37-07:00"
    },
    {
      "id": 39795561562314,
      "title": "Medium",
      "option1": "Medium",
      "option2": null,
      "option3": null,
      "sku": "B5C1R-UB9P-M",
      "requires_shipping": true,
      "taxable": true,
      "featured_image": null,
      "available": true,
      "price": "36.00",
      "grams": 0,
      "compare_at_price": null,
      "position": 4,
      "product_id": 6806352822474,
      "created_at": "2025-02-06T03:42:54-08:00",
      "updated_at": "2025-09-22T08:44:37-07:00"
    },
    {
      "id": 39795560972490,
      "title": "Large",
      "option1": "Large",
      "option2": null,
      "option3": null,
      "sku": "B5C1R-UB9P-L",
      "requires_shipping": true,
      "taxable": true,
      "featured_image": null,
      "available": true,
      "price": "36.00",
      "grams": 0,
      "compare_at_price": null,
      "position": 5,
      "product_id": 6806352822474,
      "created_at": "2025-02-06T03:42:45-08:00",
      "updated_at": "2025-09-22T08:44:37-07:00"
    },
    {
      "id": 39795532431562,
      "title": "Extra Large",
      "option1": "Extra Large",
      "option2": null,
      "option3": null,
      "sku": "B5C1R-UB9P-XL",
      "requires_shipping": true,
      "taxable": true,
      "featured_image": null,
      "available": true,
      "price": "36.00",
      "grams": 0,
      "compare_at_price": null,
      "position": 6,
      "product_id": 6806352822474,
      "created_at": "2025-02-06T03:36:32-08:00",
      "updated_at": "2025-09-22T08:44:37-07:00"
    },
    {
      "id": 39795567984842,
      "title": "Extra Extra Large",
      "option1": "Extra Extra Large",
      "option2": null,
      "option3": null,
      "sku": "B5C1R-UB9P-XXL",
      "requires_shipping": true,
      "taxable": true,
      "featured_image": null,
      "available": true,
      "price": "36.00",
      "grams": 0,
      "compare_at_price": null,
      "position": 7,
      "product_id": 6806352822474,
      "created_at": "2025-02-06T03:44:49-08:00",
      "updated_at": "2025-09-22T08:44:37-07:00"
    }
  ],
  "images": [
    {
      "id": 28994251817162,
      "created_at": "2025-08-12T11:05:59-07:00",
      "position": 1,
      "updated_at": "2025-09-04T01:16:27-07:00",
      "product_id": 6806352822474,
      "variant_ids": [],
      "src": "https://cdn.shopify.com/s/files/1/0156/6146/files/images-Gym_KitRibbedMidiShelfTankGSNavyB5C1R_UB9P_0475_V1b.jpg?v=1756973787",
      "width": 1692,
      "height": 2018
    },
    {
      "id": 28994252046538,
      "created_at": "2025-08-12T11:05:59-07:00",
      "position": 2,
      "updated_at": "2025-09-04T01:16:27-07:00",
      "product_id": 6806352822474,
      "variant_ids": [],
      "src": "https://cdn.shopify.com/s/files/1/0156/6146/files/images-Gym_KitRibbedMidiShelfTankGSNavyB5C1R_UB9P_0497_V1.jpg?v=1756973787",
      "width": 1692,
      "height": 2018
    },
    {
      "id": 28994251849930,
      "created_at": "2025-08-12T11:05:59-07:00",
      "position": 3,
      "updated_at": "2025-09-04T01:16:27-07:00",
      "product_id": 6806352822474,
      "variant_ids": [],
      "src": "https://cdn.shopify.com/s/files/1/0156/6146/files/images-Gym_KitRibbedMidiShelfTankGSNavyB5C1R_UB9P_0484_V1b.jpg?v=1756973787",
      "width": 1692,
      "height": 2018
    },
    {
      "id": 28994251882698,
      "created_at": "2025-08-12T11:05:59-07:00",
      "position": 4,
      "updated_at": "2025-09-04T01:16:27-07:00",
      "product_id": 6806352822474,
      "variant_ids": [],
      "src": "https://cdn.shopify.com/s/files/1/0156/6146/files/images-Gym_KitRibbedMidiShelfTankGSNavyB5C1R_UB9P_0480_V1b.jpg?v=1756973787",
      "width": 1692,
      "height": 2018
    },
    {
      "id": 28994251784394,
      "created_at": "2025-08-12T11:05:59-07:00",
      "position": 5,
      "updated_at": "2025-09-04T01:16:27-07:00",
      "product_id": 6806352822474,
      "variant_ids": [],
      "src": "https://cdn.shopify.com/s/files/1/0156/6146/files/images-Gym_KitRibbedMidiShelfTankGSNavyB5C1R_UB9P_0502_V1b.jpg?v=1756973787",
      "width": 1692,
      "height": 2018
    },
    {
      "id": 28994252079306,
      "created_at": "2025-08-12T11:05:59-07:00",
      "position": 6,
      "updated_at": "2025-09-04T01:16:27-07:00",
      "product_id": 6806352822474,
      "variant_ids": [],
      "src": "https://cdn.shopify.com/s/files/1/0156/6146/files/images-Gym_KitRibbedMidiShelfTankGSNavyB5C1R_UB9P_0493_V1b.jpg?v=1756973787",
      "width": 1692,
      "height": 2018
    },
    {
      "id": 28994251718858,
      "created_at": "2025-08-12T11:05:58-07:00",
      "position": 7,
      "updated_at": "2025-09-04T01:16:27-07:00",
      "product_id": 6806352822474,
      "variant_ids": [],
      "src": "https://cdn.shopify.com/s/files/1/0156/6146/files/images-Gym_KitRibbedMidiShelfTankGSNavyB5C1R_UB9P_0491_V1b.jpg?v=1756973787",
      "width": 1692,
      "height": 2018
    }
  ],
  "options": [
    {
      "name": "Size",
      "position": 1,
      "values": [
        "Extra Extra Small",
        "Extra Small",
        "Small",
        "Medium",
        "Large",
        "Extra Large",
        "Extra Extra Large"
      ]
    }
  ],
  "price": 36,
  "featured_image_url": "https://cdn.shopify.com/s/files/1/0156/6146/files/images-Gym_KitRibbedMidiShelfTankGSNavyB5C1R_UB9P_0475_V1b.jpg?v=1756973787",
  "images_count": 7,
  "variants_count": 7,
  "status": "active",
  "brand": "Gymshark | Be a visionary.",
  "category": "Womens Crop Tops",
  "availability": "in stock",
  "condition": "new",
  "dimensions": {}
}