{
  "id": 8046199242799,
  "title": "KPop Demon Hunters HUNTR/X Fighting Wrapping Paper",
  "handle": "kpop-demon-hunters-huntr-x-fighting-wrapping-paper",
  "body_html": "<p>Wrap your gifts in pure power with this HUNTR/X Fighting Wrapping Paper. This paper features a dynamic and action-packed design of the HUNTR/X trio, Rumi, Mira, and Zoey, ready for battle. It's the perfect way to add a jolt of energy and excitement to any gift, celebrating the group's fearless fighting spirit.</p><ul>\n<li>Repeating Pattern Design printed on 65# photo quality Satin Paper. </li>\n<li>Full color edge to edge and easy to work with when wrapping your gift.</li>\n</ul>",
  "published_at": "2025-08-25T16:35:20-04:00",
  "created_at": "2025-08-25T12:58:06-04:00",
  "updated_at": "2025-09-22T11:40:34-04:00",
  "vendor": "stickers-posters",
  "product_type": "Gift Wrap",
  "tags": [
    "81498621",
    "Gift Wrap",
    "Home and Office",
    "HUNTR/X",
    "Huntrix",
    "HUNTRX",
    "K-pop Demon Hunters",
    "KPop Demon Hunter",
    "Kpop Demon Hunters",
    "movie_id- 81498621",
    "new",
    "New Arrivals",
    "Party Supplies",
    "Shop All",
    "unisex",
    "Wrapping Paper"
  ],
  "variants": [
    {
      "id": 44453061885999,
      "title": "20 in x 30 in",
      "option1": "20 in x 30 in",
      "option2": null,
      "option3": null,
      "sku": "KPDH-101063-0001-KPDH-PC-0825-WRAP3",
      "requires_shipping": true,
      "taxable": true,
      "featured_image": {
        "id": 37507207069743,
        "product_id": 8046199242799,
        "position": 1,
        "created_at": "2025-08-25T12:58:17-04:00",
        "updated_at": "2025-08-25T12:58:19-04:00",
        "alt": "KPop Demon Hunters HUNTR/X Fighting Wrapping Paper",
        "width": 1500,
        "height": 2000,
        "src": "https://cdn.shopify.com/s/files/1/0522/8222/8911/files/KPDH-PC-0825-WRAP3_101063_MF.jpg?v=1756141099",
        "variant_ids": [
          44453061885999,
          44453061918767,
          44453061951535
        ]
      },
      "available": true,
      "price": "8.95",
      "grams": 231,
      "compare_at_price": null,
      "position": 1,
      "product_id": 8046199242799,
      "created_at": "2025-08-25T12:58:06-04:00",
      "updated_at": "2025-09-22T11:40:34-04:00"
    },
    {
      "id": 44453061918767,
      "title": "72 in x 30 in",
      "option1": "72 in x 30 in",
      "option2": null,
      "option3": null,
      "sku": "KPDH-101063-0002-KPDH-PC-0825-WRAP3",
      "requires_shipping": true,
      "taxable": true,
      "featured_image": {
        "id": 37507207069743,
        "product_id": 8046199242799,
        "position": 1,
        "created_at": "2025-08-25T12:58:17-04:00",
        "updated_at": "2025-08-25T12:58:19-04:00",
        "alt": "KPop Demon Hunters HUNTR/X Fighting Wrapping Paper",
        "width": 1500,
        "height": 2000,
        "src": "https://cdn.shopify.com/s/files/1/0522/8222/8911/files/KPDH-PC-0825-WRAP3_101063_MF.jpg?v=1756141099",
        "variant_ids": [
          44453061885999,
          44453061918767,
          44453061951535
        ]
      },
      "available": true,
      "price": "22.95",
      "grams": 458,
      "compare_at_price": null,
      "position": 2,
      "product_id": 8046199242799,
      "created_at": "2025-08-25T12:58:06-04:00",
      "updated_at": "2025-09-22T11:40:34-04:00"
    },
    {
      "id": 44453061951535,
      "title": "144 in x 30 in",
      "option1": "144 in x 30 in",
      "option2": null,
      "option3": null,
      "sku": "KPDH-101063-0003-KPDH-PC-0825-WRAP3",
      "requires_shipping": true,
      "taxable": true,
      "featured_image": {
        "id": 37507207069743,
        "product_id": 8046199242799,
        "position": 1,
        "created_at": "2025-08-25T12:58:17-04:00",
        "updated_at": "2025-08-25T12:58:19-04:00",
        "alt": "KPop Demon Hunters HUNTR/X Fighting Wrapping Paper",
        "width": 1500,
        "height": 2000,
        "src": "https://cdn.shopify.com/s/files/1/0522/8222/8911/files/KPDH-PC-0825-WRAP3_101063_MF.jpg?v=1756141099",
        "variant_ids": [
          44453061885999,
          44453061918767,
          44453061951535
        ]
      },
      "available": true,
      "price": "43.95",
      "grams": 1361,
      "compare_at_price": null,
      "position": 3,
      "product_id": 8046199242799,
      "created_at": "2025-08-25T12:58:06-04:00",
      "updated_at": "2025-09-22T11:40:34-04:00"
    }
  ],
  "images": [
    {
      "id": 37507207069743,
      "created_at": "2025-08-25T12:58:17-04:00",
      "position": 1,
      "updated_at": "2025-08-25T12:58:19-04:00",
      "product_id": 8046199242799,
      "variant_ids": [
        44453061885999,
        44453061918767,
        44453061951535
      ],
      "src": "https://cdn.shopify.com/s/files/1/0522/8222/8911/files/KPDH-PC-0825-WRAP3_101063_MF.jpg?v=1756141099",
      "width": 1500,
      "height": 2000
    },
    {
      "id": 37507207102511,
      "created_at": "2025-08-25T12:58:17-04:00",
      "position": 2,
      "updated_at": "2025-08-25T12:58:19-04:00",
      "product_id": 8046199242799,
      "variant_ids": [],
      "src": "https://cdn.shopify.com/s/files/1/0522/8222/8911/files/KPDH-PC-0825-WRAP3_101063_RO.jpg?v=1756141099",
      "width": 1500,
      "height": 2000
    },
    {
      "id": 37507207135279,
      "created_at": "2025-08-25T12:58:17-04:00",
      "position": 3,
      "updated_at": "2025-08-25T12:58:19-04:00",
      "product_id": 8046199242799,
      "variant_ids": [],
      "src": "https://cdn.shopify.com/s/files/1/0522/8222/8911/files/KPDH-PC-0825-WRAP3_101063_LIFE.jpg?v=1756141099",
      "width": 1500,
      "height": 2000
    }
  ],
  "options": [
    {
      "name": "Size",
      "position": 1,
      "values": [
        "20 in x 30 in",
        "72 in x 30 in",
        "144 in x 30 in"
      ]
    }
  ],
  "price": 8.95,
  "featured_image_url": "https://cdn.shopify.com/s/files/1/0522/8222/8911/files/KPDH-PC-0825-WRAP3_101063_MF.jpg?v=1756141099",
  "images_count": 3,
  "variants_count": 3,
  "status": "active",
  "brand": "stickers-posters",
  "category": "Gift Wrap",
  "availability": "in stock",
  "condition": "new",
  "dimensions": {}
}