{
  "id": 8406074818648,
  "title": "Seashell Palmography iPhone 13 Pro Case",
  "handle": "seashell-palmography-eco-friendly-iphone-13-pro-case",
  "body_html": "<p data-start=\"0\" data-end=\"79\">Say hello to your daily dose of wanderlust: the Palmography Phone Case 🌴🧡</p>\n<p data-start=\"81\" data-end=\"357\">This palm-packed pattern is a scrapbook of sunshine, splashed with doodle-style palms, wavy lines, and tropical frames that scream “wish you were here!” in the cutest way possible. With juicy orange, leafy green, and sandy tones, it’s basically a beach postcard you can carry.</p>\n<p>Beautifully designed, Pela cases are the world's first truly sustainable phone case. They are durable enough to protect your phone from drops and scratches and are also compostable!</p>",
  "published_at": "2025-07-10T08:57:37-04:00",
  "created_at": "2025-06-17T14:37:27-04:00",
  "updated_at": "2025-09-22T15:13:41-04:00",
  "vendor": "Pela Case",
  "product_type": "iPhone 13 Pro",
  "tags": [
    "art-type:Print",
    "collection:Tropical Plants",
    "Made to Order",
    "made-in:north-america",
    "magsafe compatible",
    "name:Palmography",
    "Phone Case",
    "product_notice_2",
    "protection-level:2"
  ],
  "variants": [
    {
      "id": 42990985838680,
      "title": "Default Title",
      "option1": "Default Title",
      "option2": null,
      "option3": null,
      "sku": "blank:16761-IP13P-SEASHELL-AOD:PALMOGRAPHY",
      "requires_shipping": true,
      "taxable": true,
      "featured_image": null,
      "available": true,
      "price": "65.00",
      "grams": 0,
      "compare_at_price": "65.00",
      "position": 1,
      "product_id": 8406074818648,
      "created_at": "2025-06-17T14:37:28-04:00",
      "updated_at": "2025-09-22T15:13:41-04:00"
    }
  ],
  "images": [
    {
      "id": 35241724608600,
      "created_at": "2025-06-17T14:37:27-04:00",
      "position": 1,
      "updated_at": "2025-06-17T14:37:30-04:00",
      "product_id": 8406074818648,
      "variant_ids": [],
      "src": "https://cdn.shopify.com/s/files/1/0078/1032/files/PALMOGRAPHY_IP13P_Seashell.jpg?v=1750185450",
      "width": 2000,
      "height": 2000
    },
    {
      "id": 35359267127384,
      "created_at": "2025-07-04T14:13:18-04:00",
      "position": 2,
      "updated_at": "2025-07-04T14:13:18-04:00",
      "product_id": 8406074818648,
      "variant_ids": [],
      "src": "https://cdn.shopify.com/s/files/1/0078/1032/files/13402465d73fa331493153863c3f244e_947e50a2-ad6c-47d1-be89-50bdc5ab6cb5.jpg?v=1751652798",
      "width": 4480,
      "height": 4480
    },
    {
      "id": 35359267618904,
      "created_at": "2025-07-04T14:13:20-04:00",
      "position": 3,
      "updated_at": "2025-07-04T14:13:20-04:00",
      "product_id": 8406074818648,
      "variant_ids": [],
      "src": "https://cdn.shopify.com/s/files/1/0078/1032/files/39d9ef441d1e14b3e82ca8f63f5b7629_5c10fd34-7096-4cc8-8809-15e041e5358a.jpg?v=1751652800",
      "width": 4480,
      "height": 4480
    },
    {
      "id": 35359267946584,
      "created_at": "2025-07-04T14:13:22-04:00",
      "position": 4,
      "updated_at": "2025-07-04T14:13:22-04:00",
      "product_id": 8406074818648,
      "variant_ids": [],
      "src": "https://cdn.shopify.com/s/files/1/0078/1032/files/99f0bfcc039339d1e88256b7459212b1_e4b0fad8-7d0a-4fcf-9139-1a98a24880da.jpg?v=1751652802",
      "width": 3886,
      "height": 3886
    }
  ],
  "options": [
    {
      "name": "Title",
      "position": 1,
      "values": [
        "Default Title"
      ]
    }
  ],
  "price": 65,
  "compare_at_price": 65,
  "featured_image_url": "https://cdn.shopify.com/s/files/1/0078/1032/files/PALMOGRAPHY_IP13P_Seashell.jpg?v=1750185450",
  "images_count": 4,
  "variants_count": 1,
  "status": "active",
  "brand": "Pela Case",
  "category": "iPhone 13 Pro",
  "availability": "in stock",
  "condition": "new",
  "dimensions": {}
}