{
  "id": 8387450765400,
  "title": "Seashell Ketchup Party iPhone 6/6s/7/8/SE Case",
  "handle": "seashell-ketchup-party-eco-friendly-iphone-6-6s-7-8-se-case",
  "body_html": "<p><meta charset=\"utf-8\">Squeeze some extra fun into your day with the Ketchup Party Phone Case! 🍅 From classic bottles to cheeky little packets, this case is a full-blown tomato celebration. Whether you're a fries-first kind of person or just love a good condiment moment, this playful print is here to ketchup with your boldest looks. Saucy, sweet, and totally irresistible.</p>\n<p>Beautifully designed, Pela cases are the world's first truly sustainable phone case. They are durable enough to protect your phone from drops and scratches and are also compostable!</p>",
  "published_at": "2025-06-03T09:10:32-04:00",
  "created_at": "2025-05-29T09:47:37-04:00",
  "updated_at": "2025-09-22T15:13:56-04:00",
  "vendor": "Pela Case",
  "product_type": "iPhone 6/6s/7/8/SE",
  "tags": [
    "art-type:Print",
    "collection:Condiments",
    "Made to Order",
    "made-in:north-america",
    "name:Ketchup Party",
    "Phone Case",
    "product_notice_2",
    "protection-level:2"
  ],
  "variants": [
    {
      "id": 42915147874392,
      "title": "Default Title",
      "option1": "Default Title",
      "option2": null,
      "option3": null,
      "sku": "blank:32744-IP7-SEASHELL-AOD:KETCHUP-PARTY",
      "requires_shipping": true,
      "taxable": true,
      "featured_image": null,
      "available": true,
      "price": "52.00",
      "grams": 0,
      "compare_at_price": "65.00",
      "position": 1,
      "product_id": 8387450765400,
      "created_at": "2025-05-29T09:47:37-04:00",
      "updated_at": "2025-09-22T15:13:56-04:00"
    }
  ],
  "images": [
    {
      "id": 35118016856152,
      "created_at": "2025-05-29T09:47:37-04:00",
      "position": 1,
      "updated_at": "2025-05-29T09:47:39-04:00",
      "product_id": 8387450765400,
      "variant_ids": [],
      "src": "https://cdn.shopify.com/s/files/1/0078/1032/files/KETCHUP-PARTY_IP7_Seashell.jpg?v=1748526459",
      "width": 2000,
      "height": 2000
    },
    {
      "id": 35144538128472,
      "created_at": "2025-06-02T15:00:49-04:00",
      "position": 2,
      "updated_at": "2025-06-02T15:00:49-04:00",
      "product_id": 8387450765400,
      "variant_ids": [],
      "src": "https://cdn.shopify.com/s/files/1/0078/1032/files/41b423a81da2da707f43edfc1c4b507c_16921e97-5c8f-43b3-99b8-e82408e8e36e.jpg?v=1748890849",
      "width": 810,
      "height": 810
    },
    {
      "id": 35144538357848,
      "created_at": "2025-06-02T15:00:51-04:00",
      "position": 3,
      "updated_at": "2025-06-02T15:00:51-04:00",
      "product_id": 8387450765400,
      "variant_ids": [],
      "src": "https://cdn.shopify.com/s/files/1/0078/1032/files/bc9761de247ddc7ed7da4f0a83bdae7f_7367d16d-8337-455f-b95a-0d90b6e8aa02.jpg?v=1748890851",
      "width": 810,
      "height": 810
    },
    {
      "id": 35144538652760,
      "created_at": "2025-06-02T15:00:52-04:00",
      "position": 4,
      "updated_at": "2025-06-02T15:00:52-04:00",
      "product_id": 8387450765400,
      "variant_ids": [],
      "src": "https://cdn.shopify.com/s/files/1/0078/1032/files/57be3b38d7cf0f699a7d77477d4ccdbd_c698f26c-7cca-4f61-b2c9-20080fb774f9.jpg?v=1748890852",
      "width": 810,
      "height": 810
    },
    {
      "id": 35144539045976,
      "created_at": "2025-06-02T15:00:54-04:00",
      "position": 5,
      "updated_at": "2025-06-02T15:00:54-04:00",
      "product_id": 8387450765400,
      "variant_ids": [],
      "src": "https://cdn.shopify.com/s/files/1/0078/1032/files/871b4f0c01922c9ff6937d7fdb5bb8c2_03a6d1bc-3ec4-4a9f-9b60-88a7a770ee08.jpg?v=1748890854",
      "width": 810,
      "height": 810
    },
    {
      "id": 35144539570264,
      "created_at": "2025-06-02T15:00:56-04:00",
      "position": 6,
      "updated_at": "2025-06-02T15:00:56-04:00",
      "product_id": 8387450765400,
      "variant_ids": [],
      "src": "https://cdn.shopify.com/s/files/1/0078/1032/files/a89c54d27eda82358a899ec594e79dd2_567fbe65-bed6-4695-bf7e-bb9880f31ad8.jpg?v=1748890856",
      "width": 810,
      "height": 810
    }
  ],
  "options": [
    {
      "name": "Title",
      "position": 1,
      "values": [
        "Default Title"
      ]
    }
  ],
  "price": 52,
  "compare_at_price": 65,
  "featured_image_url": "https://cdn.shopify.com/s/files/1/0078/1032/files/KETCHUP-PARTY_IP7_Seashell.jpg?v=1748526459",
  "images_count": 6,
  "variants_count": 1,
  "status": "active",
  "brand": "Pela Case",
  "category": "iPhone 6/6s/7/8/SE",
  "availability": "in stock",
  "condition": "new",
  "dimensions": {}
}